{
  "Name": "REMINDER",
  "DisplayName": "Upcoming Reservation",
  "Description": "Email sent to customer to remind about upcoming reservation request",
  "SUBJECT": "{{I18N.REMINDER.SUBJECT}}",
  "PREHEADER": "{{I18N.REMINDER.PREHEADER}}",
  "HEADER": "{{I18N.REMINDER.HEADER}}",
  "ContentTemplate": {
    "sms": "{{I18N.REMINDER.TEXT}}",
    "push": "{{I18N.REMINDER.TEXT}}"
  },
  "MAINMESSAGE": {
    "Content": "{{I18N.REMINDER.MAINMESSAGE}}"
  },
  "Booking": {
    "ButtonText": "{{I18N.LABELS.MANAGERESERVATION}}",
    "ButtonUrl": "{{Booking.Links.GuestReservationViewUrl}}"
  }
}
