{
  "Name": "Rejected",
  "DisplayName": "Reservation Rejected",
  "Description": "Email sent to customer to reject reservation request",
  "Subject": "{{i18n.Rejected.SUBJECT}}",
  "Preheader": "{{i18n.Rejected.PREHEADER}}",
  "ContentTemplate": {
    "sms": "{{i18n.Rejected.TEXT}}",
    "push": "{{i18n.Rejected.TEXT}}"
  },
  "MainMessage": {
    "Header":"{{i18n.Rejected.Header}}",
  "Title": null,
    "Content": "{{i18n.Rejected.MAINMESSAGE}}",
    "ButttonText": null,
    "ButtonUrl": null
  },
  "Booking": {
    "butttonText": "{{i18n.LABELS.MANAGERESERVATION}}"
  }
}
